MANIFEST.in
README.rst
pyproject.toml
setup.cfg
setup.py
administration/__init__.py
administration/admin.py
administration/apps.py
administration/forms.py
administration/models.py
administration/tests.py
administration/urls.py
administration/views.py
administration/migrations/0001_initial.py
administration/migrations/__init__.py
administration/templates/administration_layout/layout/administration_report.html
administration/templates/administration_layout/layout/aldeia_dropdown.html
administration/templates/administration_layout/layout/attendance.html
administration/templates/administration_layout/layout/attendanceForm.html
administration/templates/administration_layout/layout/category.html
administration/templates/administration_layout/layout/communityLeadership.html
administration/templates/administration_layout/layout/communityLeadershipForm.html
administration/templates/administration_layout/layout/complaint.html
administration/templates/administration_layout/layout/complaintForm.html
administration/templates/administration_layout/layout/decisionVillageAdvise.html
administration/templates/administration_layout/layout/decisionVillageAdviseForm.html
administration/templates/administration_layout/layout/decisionVillageChief.html
administration/templates/administration_layout/layout/decisionVillageChiefForm.html
administration/templates/administration_layout/layout/expedition.html
administration/templates/administration_layout/layout/expeditionForm.html
administration/templates/administration_layout/layout/inventory.html
administration/templates/administration_layout/layout/inventoryForm.html
administration/templates/administration_layout/layout/letterIn.html
administration/templates/administration_layout/layout/letterInForm.html
administration/templates/administration_layout/layout/letterOut.html
administration/templates/administration_layout/layout/letterOutForm.html
administration/templates/administration_layout/layout/meeting.html
maetl_administration.egg-info/PKG-INFO
maetl_administration.egg-info/SOURCES.txt
maetl_administration.egg-info/dependency_links.txt
maetl_administration.egg-info/requires.txt
maetl_administration.egg-info/top_level.txt